{"cameraMode":{"drawMode":0,"name":"Shaded","section":"Shading Mode"},"sceneLighting":true,"audioPlay":false,"sceneViewState":{"m_AlwaysRefresh":false,"showFog":true,"showSkybox":true,"showFlares":true,"showImageEffects":true,"showParticleSystems":true,"showVisualEffectGraphs":true,"m_FxEnabled":true},"in2DMode":false,"pivot":{"x":4.822467803955078,"y":-8.279634475708008,"z":0.787634551525116},"rotation":{"x":-0.1945745199918747,"y":0.5591589212417603,"z":-0.1370483636856079,"w":-0.7941251993179321},"size":10.682685852050782,"orthographic":false}